radix/__init__.py
radix/binary.py
radix/complement.py
radix/expr.py
radix/radix.py
radix_ops-0.3.5.dist-info/LICENSE
radix_ops-0.3.5.dist-info/METADATA
radix_ops-0.3.5.dist-info/WHEEL
radix_ops-0.3.5.dist-info/top_level.txt
radix_ops-0.3.5.dist-info/RECORD
