Metadata-Version: 2.1
Name: radix-ops
Version: 0.3.5
Summary: Convert between radices and perform arithmetic.
Home-page: https://github.com/deb17/radix
Author: Debashish Palit
Author-email: dpalit17@outlook.com
License: UNKNOWN
Platform: UNKNOWN
Classifier: Development Status :: 3 - Alpha
Classifier: Intended Audience :: Developers
Classifier: Programming Language :: Python :: 3
Classifier: License :: OSI Approved :: MIT License
Classifier: Operating System :: OS Independent
Requires-Python: >=3.6
